tests/__init__.py
tests/test_html_parser.py
tests/test_parsing.py
tests/test_utils.py
tests/test_wikitext.py
wiktionnaireparser/__init__.py
wiktionnaireparser/parser.py
wiktionnaireparser/parsing.py
wiktionnaireparser/utils.py
wiktionnaireparser/wikitext.py
wiktionnaireparser-0.1.dist-info/LICENSE.md
wiktionnaireparser-0.1.dist-info/METADATA
wiktionnaireparser-0.1.dist-info/WHEEL
wiktionnaireparser-0.1.dist-info/top_level.txt
wiktionnaireparser-0.1.dist-info/RECORD
