Metadata-Version: 2.1
Name: wiktionnaireparser
Version: 0.1
Summary: A library for parsing the french wiktionnary
Home-page: https://github.com/Surkal/WiktionnaireParser
Author: Surkal
License: UNKNOWN
Platform: UNKNOWN
Classifier: Programming Language :: Python :: 3
Classifier: Development Status :: 1 - Planning
Classifier: License :: OSI Approved :: GNU General Public License v3 (GPLv3)
Classifier: Topic :: Text Processing
Classifier: Natural Language :: English
Classifier: Natural Language :: French
Requires-Python: >=3.6
Requires-Dist: pytest (==6.1.1)
Requires-Dist: wikitextparser (==0.45.2)
Requires-Dist: coverage (==5.3)
Requires-Dist: requests (==2.24.0)
Requires-Dist: pyquery (==1.4.1)
